gtpyhop/__init__.py
gtpyhop/logging_system.py
gtpyhop/main.py
gtpyhop/examples/__init__.py
gtpyhop/examples/backtracking_htn.py
gtpyhop/examples/logistics_hgn.py
gtpyhop/examples/pyhop_simple_travel_example.py
gtpyhop/examples/regression_tests.py
gtpyhop/examples/simple_hgn.py
gtpyhop/examples/simple_htn.py
gtpyhop/examples/simple_htn_acting_error.py
gtpyhop/examples/blocks_goal_splitting/README.txt
gtpyhop/examples/blocks_goal_splitting/__init__.py
gtpyhop/examples/blocks_goal_splitting/actions.py
gtpyhop/examples/blocks_goal_splitting/examples.py
gtpyhop/examples/blocks_goal_splitting/methods.py
gtpyhop/examples/blocks_gtn/README.txt
gtpyhop/examples/blocks_gtn/__init__.py
gtpyhop/examples/blocks_gtn/actions.py
gtpyhop/examples/blocks_gtn/examples.py
gtpyhop/examples/blocks_gtn/methods.py
gtpyhop/examples/blocks_hgn/__init__.py
gtpyhop/examples/blocks_hgn/actions.py
gtpyhop/examples/blocks_hgn/examples.py
gtpyhop/examples/blocks_hgn/methods.py
gtpyhop/examples/blocks_htn/__init__.py
gtpyhop/examples/blocks_htn/actions.py
gtpyhop/examples/blocks_htn/examples.py
gtpyhop/examples/blocks_htn/methods.py
gtpyhop/examples/ipc-2020-total-order/benchmarking.py
gtpyhop/examples/ipc-2020-total-order/benchmarking_quickstart.md
gtpyhop/examples/ipc-2020-total-order/Blocksworld-GTOHP/__init__.py
gtpyhop/examples/ipc-2020-total-order/Blocksworld-GTOHP/domain.py
gtpyhop/examples/ipc-2020-total-order/Blocksworld-GTOHP/ipc-2020-to-bw-gtohp-readme.md
gtpyhop/examples/ipc-2020-total-order/Blocksworld-GTOHP/problems.py
gtpyhop/examples/ipc-2020-total-order/Childsnack/__init__.py
gtpyhop/examples/ipc-2020-total-order/Childsnack/domain.py
gtpyhop/examples/ipc-2020-total-order/Childsnack/ipc-2020-to-cs-gtohp-readme.md
gtpyhop/examples/ipc-2020-total-order/Childsnack/problems.py
gtpyhop/examples/mcp-orchestration/__init__.py
gtpyhop/examples/mcp-orchestration/benchmarking.py
gtpyhop/examples/mcp-orchestration/benchmarking_quickstart.md
gtpyhop-1.7.0.dist-info/METADATA
gtpyhop-1.7.0.dist-info/WHEEL
gtpyhop-1.7.0.dist-info/licenses/LICENSE.txt
gtpyhop-1.7.0.dist-info/RECORD
