Metadata-Version: 2.4
Name: gtpyhop
Version: 1.7.0
Summary: A Goal-Task-Network planning package written in Python
Project-URL: Homepage, https://github.com/PCfVW/GTPyhop/tree/pip
Project-URL: Documentation, https://github.com/dananau/GTPyhop/blob/main/additional_information.md
Project-URL: Repository, https://github.com/PCfVW/GTPyhop.git
Project-URL: Issues, https://github.com/PCfVW/GTPyhop/issues
Author-email: Eric Jacopin <eric.jacopin@protonmail.com>, Dana Nau <nau@umd.edu>
License: Clear BSD License
License-File: LICENSE.txt
Keywords: Artificial Intelligence,Automated Planning,HTN,Planning
Classifier: Development Status :: 5 - Production/Stable
Classifier: Intended Audience :: Science/Research
Classifier: License :: OSI Approved :: BSD License
Classifier: Operating System :: OS Independent
Classifier: Programming Language :: Python :: 3
Classifier: Topic :: Scientific/Engineering :: Artificial Intelligence
Requires-Python: >=3
